generate_training_data_ml/LICENSE
generate_training_data_ml/README.MD
generate_training_data_ml/__init__.py
generate_training_data_ml/requirements.txt
generate_training_data_ml/thirdparty.json
generate_training_data_ml-0.11.dist-info/LICENSE.rst
generate_training_data_ml-0.11.dist-info/METADATA
generate_training_data_ml-0.11.dist-info/WHEEL
generate_training_data_ml-0.11.dist-info/top_level.txt
generate_training_data_ml-0.11.dist-info/RECORD
